{"data": [{"file": "business_intelligence.py", "file_score": 94.60317460317461, "score_per_metric": {"Unittest": 100.0, "Pep8": 90.0, "Pylint": 85.71428571428571}}, {"file": "customers.py", "file_score": 95.55555555555556, "score_per_metric": {"Unittest": 100.0, "Pep8": 80.0, "Pylint": 100.0}}, {"file": "data_processing.py", "file_score": 96.86868686868686, "score_per_metric": {"Unittest": 100.0, "Pep8": 95.0, "Pylint": 90.9090909090909}}, {"file": "orders_management.py", "file_score": 83.05555555555556, "score_per_metric": {"Unittest": 70.0, "Pep8": 90.0, "Pylint": 93.75}}, {"file": "parking_management.py", "file_score": 0.0, "score_per_metric": {"Unittest": 0, "Pep8": 95.0, "Pylint": 0}}, {"file": "statistics.py", "file_score": 59.68253968253968, "score_per_metric": {"Unittest": 14.285714285714286, "Pep8": 90.0, "Pylint": 100.0}}, {"file": "text_analysis.py", "file_score": 0.0, "score_per_metric": {"Unittest": 0, "Pep8": 90.0, "Pylint": 40.0}}, {"file": "transactions.py", "file_score": 0.0, "score_per_metric": {"Unittest": 0, "Pep8": 95.0, "Pylint": 50.0}}], "overall_score": 53.72068903318904}